{
  "id": "Q107863024",
  "name": "Gireba",
  "description": "Gireba is a Northern Nigeria delicacy derived from flour, and is made with everyday easily digestible ingredients. Flour is a powder made by grinding raw grains, roots, beans, nuts, or seeds.",
  "nationality": [],
  "region_cuisine": [],
  "images": [
    "images/gireba-q107863024/gireba-q107863024-1.jpg",
    "images/gireba-q107863024/gireba-q107863024-2.jpg"
  ],
  "recipe": null,
  "sources": {
    "wikidata": "https://www.wikidata.org/wiki/Q107863024",
    "themealdb": null
  }
}