{
  "id": "Q11675829",
  "name": "chicken ham",
  "description": "",
  "nationality": [
    "British"
  ],
  "region_cuisine": [
    "Chicken"
  ],
  "images": [
    "images/chicken-ham-q11675829/chicken-ham-q11675829-1.jpg",
    "images/chicken-ham-q11675829/chicken-ham-q11675829-2.jpg",
    "images/chicken-ham-q11675829/chicken-ham-q11675829-3.jpg",
    "images/chicken-ham-q11675829/chicken-ham-q11675829-4.jpg"
  ],
  "recipe": {
    "source": "TheMealDB",
    "source_id": "52875",
    "category": "Chicken",
    "area": "British",
    "instructions": "Heat the chicken stock in a lidded saucepan. Add the chicken breast and bring to a low simmer. Cover with a lid and cook for 10 minutes. Remove the chicken breasts from the water with tongs and place on a plate. Pour the cooking liquor into a large jug.\r\nMelt 25g/1oz of the butter in a large heavy-based saucepan over a low heat. Stir in the leeks and fry gently for two minutes, stirring occasionally until just softened. Add the garlic and cook for a further minute. Add the remaining butter and stir in the flour as soon as the butter has melted. Cook for 30 seconds, stirring constantly.\r\nSlowly pour the milk into the pan, just a little at a time, stirring well between each adding. Gradually add 250ml/10fl oz of the reserved stock and the wine, if using, stirring until the sauce is smooth and thickened slightly. Bring to a gentle simmer and cook for 3 minutes.\r\nSeason the mixture, to taste, with salt and freshly ground black pepper. Remove from the heat and stir in the cream. Pour into a large bowl and cover the surface of the sauce with cling ilm to prevent a skin forming. Set aside to cool.\r\nPreheat the oven to 200C/400F/Gas 6. Put a baking tray in the oven to heat.\r\nFor the pastry, put the flour and butter in a food processor and blend on the pulse setting until the mixture resembles fine breadcrumbs. With the motor running, add the beaten egg and water and blend until the mixture forms a ball. Portion off 250g/10oz of pastry for the lid.\r\nRoll the remaining pastry out on a lightly floured surface, turning the pastry frequently until around 5mm/¼in thick and 4cm/1½in larger than the pie dish. Lift the pastry over the rolling pin and place it gently into the pie dish. Press the pastry firmly up the sides, making sure there are no air bubbles. Leave the excess pastry overhanging the sides.\r\nCut the chicken breasts into 3cm/1¼in pieces. Stir the chicken, ham and leeks into the cooled sauce. Pour the chicken filling into the pie dish. Brush the rim of the dish with beaten egg. Roll out the reserved pastry for the lid.\r\nCover the pie with the pastry lid and press the edges together firmly to seal. Trim any excess pastry.\r\nMake a small hole in the centre of the pie with the tip of a knife. Glaze the top of the pie with beaten egg. Bake on the preheated tray in the centre of the oven for 35-40 minutes or until the pie is golden-brown all over and the filling is piping hot.",
    "ingredients": [
      {
        "ingredient": "Chicken Stock",
        "measure": "450ml"
      },
      {
        "ingredient": "Chicken Breast",
        "measure": "3"
      },
      {
        "ingredient": "Butter",
        "measure": "75g"
      },
      {
        "ingredient": "Leek",
        "measure": "2 sliced"
      },
      {
        "ingredient": "Garlic",
        "measure": "2 cloves minced"
      },
      {
        "ingredient": "Plain Flour",
        "measure": "50g"
      },
      {
        "ingredient": "Milk",
        "measure": "200ml"
      },
      {
        "ingredient": "White Wine",
        "measure": "3 tbs"
      },
      {
        "ingredient": "Double Cream",
        "measure": "150ml"
      },
      {
        "ingredient": "Ham",
        "measure": "150g"
      },
      {
        "ingredient": "Sea Salt",
        "measure": "spinkling"
      },
      {
        "ingredient": "Pepper",
        "measure": "pinch"
      },
      {
        "ingredient": "Plain Flour",
        "measure": "350g"
      },
      {
        "ingredient": "Butter",
        "measure": "200g"
      },
      {
        "ingredient": "Free-range Egg, Beaten",
        "measure": "1"
      },
      {
        "ingredient": "Cold Water",
        "measure": "1 tbls"
      },
      {
        "ingredient": "Free-range Egg, Beaten",
        "measure": "1"
      }
    ],
    "youtube": "https://www.youtube.com/watch?v=xr-CpPE_lNk",
    "thumb": "https://www.themealdb.com/images/media/meals/xrrtss1511555269.jpg"
  },
  "sources": {
    "wikidata": "https://www.wikidata.org/wiki/Q11675829",
    "themealdb": "52875"
  }
}