{
  "id": "Q15427731",
  "name": "kumpir",
  "description": "Turkish baked potato dish",
  "nationality": [
    "Turkey"
  ],
  "region_cuisine": [
    "Side"
  ],
  "images": [
    "images/kumpir-q15427731/kumpir-q15427731-1.jpg",
    "images/kumpir-q15427731/kumpir-q15427731-2.jpg",
    "images/kumpir-q15427731/kumpir-q15427731-3.jpg",
    "images/kumpir-q15427731/kumpir-q15427731-4.jpg"
  ],
  "recipe": {
    "source": "TheMealDB",
    "source_id": "52978",
    "category": "Side",
    "area": "Turkish",
    "instructions": "If you order kumpir in Turkey, the standard filling is first, lots of butter mashed into the potato, followed by cheese. There’s then a row of other toppings that you can just point at to your heart’s content – sweetcorn, olives, salami, coleslaw, Russian salad, allsorts – and you walk away with an over-stuffed potato because you got ever-excited by the choices on offer.\r\n\r\nGrate (roughly – you can use as much as you like) 150g of cheese.\r\nFinely chop one onion and one sweet red pepper.\r\nPut these ingredients into a large bowl with a good sprinkling of salt and pepper, chilli flakes (optional).",
    "ingredients": [
      {
        "ingredient": "Potatoes",
        "measure": "2 large"
      },
      {
        "ingredient": "Butter",
        "measure": "2 tbs"
      },
      {
        "ingredient": "Cheese",
        "measure": "150g"
      },
      {
        "ingredient": "Onion",
        "measure": "1 large"
      },
      {
        "ingredient": "Red Pepper",
        "measure": "1 large"
      },
      {
        "ingredient": "Red Chilli Flakes",
        "measure": "Pinch"
      }
    ],
    "youtube": "https://www.youtube.com/watch?v=IEDEtZ4UVtI",
    "thumb": "https://www.themealdb.com/images/media/meals/mlchx21564916997.jpg"
  },
  "sources": {
    "wikidata": "https://www.wikidata.org/wiki/Q15427731",
    "themealdb": "52978"
  }
}