{
  "id": "Q6981917",
  "name": "pölsa",
  "description": "traditional Swedish dish made from finely ground meat, traditionally leftover meat",
  "nationality": [
    "Sweden"
  ],
  "region_cuisine": [],
  "images": [
    "images/polsa-q6981917/polsa-q6981917-1.jpg",
    "images/polsa-q6981917/polsa-q6981917-2.jpg",
    "images/polsa-q6981917/polsa-q6981917-3.jpg",
    "images/polsa-q6981917/polsa-q6981917-4.jpg"
  ],
  "recipe": null,
  "sources": {
    "wikidata": "https://www.wikidata.org/wiki/Q6981917",
    "themealdb": null
  }
}